{
  "major_title": "Economics/Mathematics Combined B.A.",
  "sending_school": "College of San Mateo",
  "receiving_school": "University of California, Santa Cruz",
  "options": {
    "REQUIRED MAJOR PREPARATION COURSES": [
      {
        "label": "A",
        "block_number": "1",
        "instructions": "Complete the following",
        "attribute": "",
        "group_type": "",
        "courses": [
          {
            "receiving_course": {
              "prefix": "ECON 1",
              "title": "Introductory Microeconomics: Resource Allocation and Market Structure",
              "units": "5.00units"
            },
            "sending_courses": [
              {
                "prefix": "ECON 102",
                "title": "Principles of Microeconomics",
                "units": "3.00units",
                "conjunction": ""
              }
            ],
            "status": "articulated"
          },
          {
            "receiving_course": {
              "prefix": "ECON 2",
              "title": "Introductory Macroeconomics: Aggregate Economic Activity",
              "units": "5.00units"
            },
            "sending_courses": [
              {
                "prefix": "ECON 100",
                "title": "Principles of Macroeconomics",
                "units": "3.00units",
                "conjunction": ""
              }
            ],
            "status": "articulated"
          },
          {
            "receiving_course": {
              "prefix": "MATH 19A",
              "title": "Calculus for Science, Engineering, and Mathematics",
              "units": "5.00units"
            },
            "sending_courses": [
              {
                "prefix": "MATH 251",
                "title": "Calculus with Analytic Geometry I",
                "units": "5.00units",
                "conjunction": ""
              }
            ],
            "status": "articulated"
          }
        ]
      }
    ],
    "RECOMMENDED PREPARATION": [
      {
        "label": "A",
        "block_number": "2",
        "instructions": "Complete the following",
        "attribute": "Highly recommended",
        "group_type": "",
        "courses": [
          {
            "receiving_course": {
              "prefix": "MATH 19B",
              "title": "Calculus for Science, Engineering, and Mathematics",
              "units": "5.00units"
            },
            "sending_courses": [
              {
                "prefix": "MATH 252",
                "title": "Calculus with Analytic Geometry II",
                "units": "5.00units",
                "conjunction": ""
              }
            ],
            "status": "articulated"
          }
        ]
      },
      {
        "label": "A",
        "block_number": "3",
        "instructions": "CompleteAorB",
        "attribute": "Highly recommended",
        "group_type": "",
        "courses": [
          {
            "receiving_course": {
              "prefix": "MATH 22",
              "title": "Introduction to Calculus of Several Variables",
              "units": "5.00units"
            },
            "sending_courses": [
              {
                "prefix": "MATH 253",
                "title": "Calculus with Analytic Geometry III",
                "units": "5.00units",
                "conjunction": ""
              }
            ],
            "status": "articulated"
          }
        ]
      },
      {
        "label": "B",
        "block_number": "3",
        "instructions": "CompleteAorB",
        "attribute": "Highly recommended",
        "group_type": "",
        "courses": [
          {
            "receiving_course": {
              "prefix": "MATH 23A",
              "title": "Vector Calculus",
              "units": "5.00units"
            },
            "sending_courses": [
              {
                "prefix": "MATH 253",
                "title": "Calculus with Analytic Geometry III",
                "units": "5.00units",
                "conjunction": ""
              }
            ],
            "status": "articulated"
          },
          {
            "receiving_course": {
              "prefix": "MATH 23B",
              "title": "Vector Calculus",
              "units": "5.00units"
            },
            "sending_courses": [
              {
                "prefix": "MATH 253",
                "title": "Calculus with Analytic Geometry III",
                "units": "5.00units",
                "conjunction": ""
              }
            ],
            "status": "articulated"
          }
        ]
      }
    ],
    "ADDITIONAL MAJOR PREPARATION COURSES": [
      {
        "label": "A",
        "block_number": "4",
        "instructions": "Complete the following",
        "attribute": "",
        "group_type": "",
        "courses": [
          {
            "receiving_course": {
              "prefix": "MATH 21",
              "title": "Linear Algebra",
              "units": "5.00units"
            },
            "sending_courses": [
              {
                "prefix": "MATH 270",
                "title": "Linear Algebra",
                "units": "3.00units",
                "conjunction": ""
              }
            ],
            "status": "articulated"
          },
          {
            "receiving_course": {
              "prefix": "STAT 17",
              "title": "Statistical Methods for Business and Economics",
              "units": "5.00units"
            },
            "sending_courses": [
              {
                "prefix": "BUS. 123",
                "title": "Business Statistics",
                "units": "3.00units",
                "conjunction": ""
              }
            ],
            "status": "articulated"
          },
          {
            "receiving_course": {
              "prefix": "STAT 17L",
              "title": "Statistical Methods for Business and Economics Laboratory",
              "units": "2.00units"
            },
            "sending_courses": null,
            "status": "not_articulated"
          }
        ]
      }
    ]
  }
}